{
  "coins": 0,
  "unlocked_maps": [
    1,
    2,
    3
  ],
  "unlocked_fish": [
    "fish01",
    "fish02",
    "fish03",
    "fish04",
    "fish05",
    "fish06",
    "fish07",
    "fish08",
    "fish09",
    "fish10",
    "fish11",
    "fish12"
  ],
  "selected_fish_p1": "fish03",
  "selected_fish_p2": "fish03",
  "highscores": {
    "1": 3983,
    "2": 3977,
    "3": 5025
  },
  "history": [
    {
      "time": "2026-01-04 17:29:22",
      "mode": 1,
      "map_id": 3,
      "points": 970,
      "time_alive": 65.0210000000004,
      "result": "LOSE"
    },
    {
      "time": "2026-01-04 17:27:48",
      "mode": 1,
      "map_id": 3,
      "points": 775,
      "time_alive": 57.02100000000013,
      "result": "LOSE"
    },
    {
      "time": "2026-01-04 17:26:46",
      "mode": 1,
      "map_id": 2,
      "points": 3977,
      "time_alive": 58.49000000000082,
      "result": "WIN"
    },
    {
      "time": "2026-01-04 17:25:40",
      "mode": 1,
      "map_id": 2,
      "points": 254,
      "time_alive": 41.48899999999963,
      "result": "LOSE"
    },
    {
      "time": "2026-01-04 17:16:11",
      "mode": 1,
      "map_id": 2,
      "points": 234,
      "time_alive": 122.50900000000271,
      "result": "LOSE"
    },
    {
      "time": "2026-01-04 17:14:04",
      "mode": 1,
      "map_id": 1,
      "points": 500,
      "time_alive": 32.42699999999891,
      "result": "WIN"
    },
    {
      "time": "2026-01-04 15:48:31",
      "mode": 1,
      "map_id": 1,
      "points": 246,
      "time_alive": 47.77199999999945,
      "result": "LOSE"
    },
    {
      "time": "2026-01-04 15:47:34",
      "mode": 1,
      "map_id": 1,
      "points": 379,
      "time_alive": 67.58600000000024,
      "result": "LOSE"
    },
    {
      "time": "2026-01-04 15:42:05",
      "mode": 1,
      "map_id": 1,
      "points": 798,
      "time_alive": 60.45000000000001,
      "result": "WIN"
    },
    {
      "time": "2026-01-04 15:40:36",
      "mode": 1,
      "map_id": 1,
      "points": 995,
      "time_alive": 63.96000000000014,
      "result": "WIN"
    },
    {
      "time": "2026-01-04 15:37:25",
      "mode": 1,
      "map_id": 1,
      "points": 514,
      "time_alive": 48.96899999999942,
      "result": "WIN"
    },
    {
      "time": "2026-01-04 15:13:20",
      "mode": 1,
      "map_id": 1,
      "points": 507,
      "time_alive": 40.6019999999992,
      "result": "WIN"
    },
    {
      "time": "2026-01-03 15:51:59",
      "mode": 1,
      "map_id": 1,
      "points": 15,
      "time_alive": 20.96299999999963,
      "result": "LOSE"
    },
    {
      "time": "2026-01-03 15:51:25",
      "mode": 1,
      "map_id": 1,
      "points": 5,
      "time_alive": 8.055000000000039,
      "result": "LOSE"
    },
    {
      "time": "2026-01-03 15:42:26",
      "mode": 1,
      "map_id": 1,
      "points": 5,
      "time_alive": 19.083999999999744,
      "result": "LOSE"
    },
    {
      "time": "2026-01-03 15:39:09",
      "mode": 1,
      "map_id": 1,
      "points": 10,
      "time_alive": 18.177999999999766,
      "result": "LOSE"
    },
    {
      "time": "2026-01-03 15:38:21",
      "mode": 1,
      "map_id": 1,
      "points": 5,
      "time_alive": 6.458000000000022,
      "result": "LOSE"
    },
    {
      "time": "2026-01-03 15:11:07",
      "mode": 1,
      "map_id": 1,
      "points": 5,
      "time_alive": 5.944000000000015,
      "result": "LOSE"
    },
    {
      "time": "2026-01-03 15:03:20",
      "mode": 1,
      "map_id": 1,
      "points": 5,
      "time_alive": 11.029999999999992,
      "result": "LOSE"
    },
    {
      "time": "2026-01-03 12:03:58",
      "mode": 2,
      "map_id": 1,
      "points": 30,
      "time_alive": 38.304999999999325,
      "result": "LOSE"
    },
    {
      "time": "2026-01-03 12:03:00",
      "mode": 1,
      "map_id": 1,
      "points": 28,
      "time_alive": 43.07199999999947,
      "result": "LOSE"
    },
    {
      "time": "2026-01-03 11:43:56",
      "mode": 1,
      "map_id": 1,
      "points": 18,
      "time_alive": 9.34600000000002,
      "result": "LOSE"
    },
    {
      "time": "2026-01-03 11:43:44",
      "mode": 1,
      "map_id": 1,
      "points": 5,
      "time_alive": 15.29899999999993,
      "result": "LOSE"
    },
    {
      "time": "2026-01-03 11:28:07",
      "mode": 1,
      "map_id": 1,
      "points": 5,
      "time_alive": 14.78899999999993,
      "result": "LOSE"
    },
    {
      "time": "2026-01-03 09:02:21",
      "mode": 1,
      "map_id": 1,
      "points": 5,
      "time_alive": 6.868000000000016,
      "result": "LOSE"
    },
    {
      "time": "2026-01-03 04:24:19",
      "mode": 1,
      "map_id": 1,
      "points": 5,
      "time_alive": 8.105000000000036,
      "result": "LOSE"
    },
    {
      "time": "2026-01-03 04:18:14",
      "mode": 1,
      "map_id": 1,
      "points": 5,
      "time_alive": 3.761999999999994,
      "result": "LOSE"
    },
    {
      "time": "2026-01-03 04:18:08",
      "mode": 1,
      "map_id": 1,
      "points": 5,
      "time_alive": 9.020000000000017,
      "result": "LOSE"
    },
    {
      "time": "2026-01-03 04:15:34",
      "mode": 1,
      "map_id": 1,
      "points": 15,
      "time_alive": 9.901000000000009,
      "result": "LOSE"
    },
    {
      "time": "2026-01-03 04:15:21",
      "mode": 1,
      "map_id": 1,
      "points": 33,
      "time_alive": 19.516999999999715,
      "result": "LOSE"
    },
    {
      "time": "2026-01-03 03:51:48",
      "mode": 1,
      "map_id": 1,
      "points": 134,
      "time_alive": 37.5159999999993,
      "result": "LOSE"
    },
    {
      "time": "2026-01-03 03:19:50",
      "mode": 1,
      "map_id": 1,
      "points": 171,
      "time_alive": 33.92399999999914,
      "result": "LOSE"
    },
    {
      "time": "2026-01-03 02:12:04",
      "mode": 1,
      "map_id": 1,
      "points": 5,
      "time_alive": 12.025999999999975,
      "result": "LOSE"
    },
    {
      "time": "2026-01-03 01:11:12",
      "mode": 1,
      "map_id": 2,
      "points": 5,
      "time_alive": 24.10599999999936,
      "result": "LOSE"
    },
    {
      "time": "2026-01-03 01:10:43",
      "mode": 1,
      "map_id": 1,
      "points": 501,
      "time_alive": 59.04000000000025,
      "result": "WIN"
    },
    {
      "time": "2026-01-03 01:08:58",
      "mode": 1,
      "map_id": 1,
      "points": 18,
      "time_alive": 19.90999999999968,
      "result": "LOSE"
    },
    {
      "time": "2026-01-03 01:06:31",
      "mode": 1,
      "map_id": 2,
      "points": 5,
      "time_alive": 8.992000000000022,
      "result": "LOSE"
    },
    {
      "time": "2026-01-03 01:06:19",
      "mode": 1,
      "map_id": 1,
      "points": 548,
      "time_alive": 43.2459999999996,
      "result": "WIN"
    },
    {
      "time": "2026-01-03 00:58:27",
      "mode": 1,
      "map_id": 1,
      "points": 5,
      "time_alive": 23.871999999999407,
      "result": "LOSE"
    },
    {
      "time": "2026-01-03 00:45:23",
      "mode": 1,
      "map_id": 1,
      "points": 5,
      "time_alive": 60.70700000000005,
      "result": "LOSE"
    },
    {
      "time": "2026-01-03 00:39:12",
      "mode": 1,
      "map_id": 1,
      "points": 20,
      "time_alive": 19.830999999999705,
      "result": "LOSE"
    },
    {
      "time": "2026-01-03 00:30:47",
      "mode": 1,
      "map_id": 1,
      "points": 25,
      "time_alive": 13.937999999999946,
      "result": "LOSE"
    },
    {
      "time": "2026-01-02 23:41:37",
      "mode": 1,
      "map_id": 2,
      "points": 813,
      "time_alive": 9.727000000000007,
      "result": "LOSE"
    },
    {
      "time": "2026-01-02 23:41:24",
      "mode": 1,
      "map_id": 1,
      "points": 533,
      "time_alive": 71.68200000000084,
      "result": "WIN"
    },
    {
      "time": "2026-01-02 23:33:02",
      "mode": 1,
      "map_id": 1,
      "points": 5,
      "time_alive": 51.30199999999924,
      "result": "LOSE"
    },
    {
      "time": "2026-01-02 23:15:23",
      "mode": 1,
      "map_id": 1,
      "points": 5,
      "time_alive": 19.52399999999968,
      "result": "LOSE"
    },
    {
      "time": "2026-01-02 22:37:45",
      "mode": 1,
      "map_id": 1,
      "points": 5,
      "time_alive": 31.866999999998995,
      "result": "LOSE"
    },
    {
      "time": "2026-01-02 21:35:46",
      "mode": 1,
      "map_id": 1,
      "points": 514,
      "time_alive": 37.98200000000002,
      "result": "WIN"
    },
    {
      "time": "2026-01-02 21:35:04",
      "mode": 1,
      "map_id": 1,
      "points": 43,
      "time_alive": 45.80499999999988,
      "result": "LOSE"
    },
    {
      "time": "2026-01-02 21:30:24",
      "mode": 1,
      "map_id": 1,
      "points": 526,
      "time_alive": 32.22500000000013,
      "result": "WIN"
    }
  ],
  "settings": {
    "music": 0.0,
    "sfx": 0.0,
    "fullscreen": false
  }
}